tvara/__init__.py
tvara/cli/__init__.py
tvara/cli/main.py
tvara/core/__init__.py
tvara/core/agent.py
tvara/core/memory.py
tvara/core/prompt.py
tvara/core/workflow.py
tvara/logging/__init__.py
tvara/models/__init__.py
tvara/models/base.py
tvara/models/claude.py
tvara/models/gemini.py
tvara/models/model_factory.py
tvara/models/openai.py
tvara/models/supported_models.py
tvara/tools/__init__.py
tvara/tools/base.py
tvara/tools/ComposioTool.py
tvara/tools/CustomTool.py
tvara/utils/__init__.py
tvara/utils/auth_cache.py
tvara/utils/config.py
tvara/utils/logger.py
tvara/utils/prompt_templates.py
tvara/utils/validators.py
tvara/version.py
tvara-1.1.0.dist-info/entry_points.txt
tvara-1.1.0.dist-info/LICENSE
tvara-1.1.0.dist-info/METADATA
tvara-1.1.0.dist-info/WHEEL
tvara-1.1.0.dist-info/RECORD
