Metadata-Version: 2.3
Name: tvara
Version: 1.1.0
Summary: A Python package for Tvara, a tool for automating workflows.
License: MIT
Keywords: agents,AI,workflow,tvara
Author: Team Tvara
Author-email: team@tvarahq.com
Requires-Python: >=3.9,<4
Classifier: License :: OSI Approved :: MIT License
Classifier: Programming Language :: Python :: 3
Classifier: Programming Language :: Python :: 3.9
Classifier: Programming Language :: Python :: 3.10
Classifier: Programming Language :: Python :: 3.11
Classifier: Programming Language :: Python :: 3.12
Classifier: Programming Language :: Python :: 3.13
Requires-Dist: anthropic (>=0.61.0,<0.62.0)
Requires-Dist: composio (==0.8.0)
Requires-Dist: google-genai (>=1.27.0,<2.0.0)
Requires-Dist: openai (==1.99.9)
Requires-Dist: pydantic (==2.11.7)
Requires-Dist: tavily-python (>=0.7.10,<0.8.0)
Project-URL: Homepage, https://tvarahq.com
Project-URL: Repository, https://github.com/tvarahq/tvara
